setup.py
tweed/__init__.py
tweed.egg-info/PKG-INFO
tweed.egg-info/SOURCES.txt
tweed.egg-info/dependency_links.txt
tweed.egg-info/requires.txt
tweed.egg-info/top_level.txt
tweed/tests/test_tweed.py