Metadata-Version: 1.0
Name: tweed
Version: 0.1
Summary: Some extensions for twill
Home-page: UNKNOWN
Author: Matt Wilson
Author-email: matt@tplus1.com
License: PSF
Keywords: twill
Platform: UNKNOWN
